ahlive/__init__.py
ahlive/animation.py
ahlive/configuration.py
ahlive/data.py
ahlive/easing.py
ahlive/join.py
ahlive/tutorial.py
ahlive/util.py
ahlive/tests/test_configuration.py
ahlive/tests/test_data.py
ahlive/tests/test_easing.py
ahlive/tests/test_join.py
ahlive/tests/test_util.py
ahlive-1.0.4.post1.dist-info/LICENSE
ahlive-1.0.4.post1.dist-info/METADATA
ahlive-1.0.4.post1.dist-info/WHEEL
ahlive-1.0.4.post1.dist-info/top_level.txt
ahlive-1.0.4.post1.dist-info/zip-safe
ahlive-1.0.4.post1.dist-info/RECORD
