Metadata-Version: 2.1
Name: ahlive
Version: 1.0.4.post1
Summary: animate your data to life
Home-page: https://github.com/ahuang11/ahlive
Keywords: ahlive,xarray,animation,easing,interp,gif
Classifier: License :: OSI Approved :: BSD License
Classifier: Development Status :: 3 - Alpha
Classifier: Programming Language :: Python :: 3.5
Classifier: Programming Language :: Python :: 3.6
Classifier: Programming Language :: Python :: 3.7
Classifier: Programming Language :: Python :: 3.8
Classifier: Operating System :: OS Independent
Classifier: Intended Audience :: Science/Research
Classifier: Intended Audience :: Developers
Classifier: Natural Language :: English
Classifier: Framework :: Matplotlib
Classifier: Topic :: Scientific/Engineering
Classifier: Topic :: Scientific/Engineering :: Visualization
Classifier: Topic :: Software Development :: Libraries
License-File: LICENSE
Requires-Dist: param
Requires-Dist: numpy
Requires-Dist: pandas
Requires-Dist: bottleneck
Requires-Dist: xarray (>=0.16.1)
Requires-Dist: matplotlib (>=3.3)
Requires-Dist: imageio
